cdk_s3bucket/__init__.py
cdk_s3bucket/py.typed
cdk_s3bucket/_jsii/__init__.py
cdk_s3bucket/_jsii/cdk-s3bucket@0.0.3.jsii.tgz
cdk_s3bucket-0.0.3.dist-info/METADATA
cdk_s3bucket-0.0.3.dist-info/WHEEL
cdk_s3bucket-0.0.3.dist-info/top_level.txt
cdk_s3bucket-0.0.3.dist-info/RECORD
