Metadata-Version: 2.1
Name: cdk-s3bucket
Version: 0.0.3
Summary: cdk-s3bucket
Home-page: https://github.com/guan840912/cdk-s3bucket.git
Author: Neil Kuan<guan840912@gmail.com>
License: Apache-2.0
Project-URL: Source, https://github.com/guan840912/cdk-s3bucket.git
Platform: UNKNOWN
Classifier: Intended Audience :: Developers
Classifier: Operating System :: OS Independent
Classifier: Programming Language :: JavaScript
Classifier: Programming Language :: Python :: 3 :: Only
Classifier: Programming Language :: Python :: 3.6
Classifier: Programming Language :: Python :: 3.7
Classifier: Programming Language :: Python :: 3.8
Classifier: Typing :: Typed
Classifier: Development Status :: 5 - Production/Stable
Classifier: License :: OSI Approved
Requires-Python: >=3.6
Requires-Dist: aws-cdk.aws-iam (<2.0.0,>=1.62.0)
Requires-Dist: aws-cdk.aws-lambda (<2.0.0,>=1.62.0)
Requires-Dist: aws-cdk.aws-logs (<2.0.0,>=1.62.0)
Requires-Dist: aws-cdk.aws-s3 (<2.0.0,>=1.62.0)
Requires-Dist: aws-cdk.core (<2.0.0,>=1.62.0)
Requires-Dist: aws-cdk.custom-resources (<2.0.0,>=1.62.0)
Requires-Dist: constructs (<4.0.0,>=3.0.4)
Requires-Dist: jsii (<2.0.0,>=1.12.0)
Requires-Dist: publication (>=0.0.3)
